phantomjs/__init__.py
phantomjs/asynchronous.py
phantomjs/get_source.js
phantomjs/get_source_wait_for.js
phantomjs/phantom.py
phantomjs/test.py
phantomjs/testio.py
phantomjs/version.py
phantomjs-1.4.1.dist-info/LICENSE
phantomjs-1.4.1.dist-info/METADATA
phantomjs-1.4.1.dist-info/WHEEL
phantomjs-1.4.1.dist-info/top_level.txt
phantomjs-1.4.1.dist-info/RECORD
