Metadata-Version: 2.1
Name: phantomjs
Version: 1.4.1
Summary: Python wrapper for PhantomJS
Home-page: https://github.com/neurobin/phantomjspy
Author: Md. Jahidul Hamid
Author-email: jahidulhamid@yahoo.com
License: BSD
Keywords: markdown include local remote file
Platform: UNKNOWN
Classifier: Development Status :: 5 - Production/Stable
Classifier: Intended Audience :: Developers
Classifier: Intended Audience :: Information Technology
Classifier: License :: OSI Approved :: BSD License
Classifier: Operating System :: OS Independent
Classifier: Programming Language :: Python
Classifier: Programming Language :: Python :: 3
